vrin/__init__.py
vrin/agents.py
vrin/cli.py
vrin/client.py
vrin/client_v2.py
vrin/client_v3.py
vrin/config.py
vrin/conversation.py
vrin/deployment.py
vrin/enterprise.py
vrin/enterprise_client.py
vrin/exceptions.py
vrin/models.py
vrin/network.py
vrin/validation.py
vrin/providers/__init__.py
vrin/providers/database.py
vrin/providers/factory.py
vrin/providers/llm.py
vrin-0.8.0.dist-info/licenses/LICENSE
vrin-0.8.0.dist-info/METADATA
vrin-0.8.0.dist-info/WHEEL
vrin-0.8.0.dist-info/top_level.txt
vrin-0.8.0.dist-info/RECORD
