Metadata-Version: 2.4
Name: vrin
Version: 0.8.0
Summary: Enterprise Hybrid RAG SDK with entity-centric extraction, zero-loss architecture, complete source attribution, constraint solver, temporal consistency, and multi-cloud deployment
Home-page: https://github.com/vrin-ai/vrin-sdk
Author: VRIN Team
Author-email: VRIN Team <vedant@vrin.cloud>
Maintainer-email: VRIN Team <vedant@vrin.cloud>
License-Expression: MIT
Project-URL: Homepage, https://github.com/vrin-ai/vrin-python
Project-URL: Documentation, https://docs.vrin.ai
Project-URL: Repository, https://github.com/vrin-ai/vrin-python
Project-URL: Bug Tracker, https://github.com/vrin-ai/vrin-python/issues
Keywords: ai,knowledge-graph,memory,orchestration,context,retrieval
Classifier: Development Status :: 4 - Beta
Classifier: Intended Audience :: Developers
Classifier: Operating System :: OS Independent
Classifier: Programming Language :: Python :: 3
Classifier: Programming Language :: Python :: 3.8
Classifier: Programming Language :: Python :: 3.9
Classifier: Programming Language :: Python :: 3.10
Classifier: Programming Language :: Python :: 3.11
Classifier: Topic :: Scientific/Engineering :: Artificial Intelligence
Classifier: Topic :: Software Development :: Libraries :: Python Modules
Requires-Python: >=3.8
License-File: LICENSE
Requires-Dist: requests>=2.25.0
Requires-Dist: typing-extensions>=3.7.4
Provides-Extra: dev
Requires-Dist: pytest>=6.0; extra == "dev"
Requires-Dist: pytest-cov>=2.0; extra == "dev"
Requires-Dist: black>=21.0; extra == "dev"
Requires-Dist: flake8>=3.8; extra == "dev"
Requires-Dist: mypy>=0.800; extra == "dev"
Dynamic: author
Dynamic: home-page
Dynamic: license-file
Dynamic: requires-python
